HPO/__init__.py
HPO/general_utils.py
HPO/algorithms/Greedy.py
HPO/algorithms/Join.py
HPO/algorithms/NASWOT.py
HPO/algorithms/Random.py
HPO/algorithms/TS-greedy.py
HPO/algorithms/WOT.py
HPO/algorithms/__init__.py
HPO/algorithms/algorithm_base.py
HPO/algorithms/algorithm_utils.py
HPO/algorithms/boot.py
HPO/algorithms/distil_search.py
HPO/algorithms/meta_cv.py
HPO/algorithms/naswot.py
HPO/algorithms/regevo.py
HPO/algorithms/regevo_DARTS.py
HPO/algorithms/regevo_DARTS_ts.py
HPO/algorithms/regevo_alt.py
HPO/algorithms/regevo_graph.py
HPO/algorithms/retrain.py
HPO/data/EEG.py
HPO/data/FORDB.py
HPO/data/HAR.py
HPO/data/SHAR.py
HPO/data/TEPS.py
HPO/data/UEA_datasets.py
HPO/data/__init__.py
HPO/data/btc_dataset.py
HPO/data/cifar100.py
HPO/data/dataset.py
HPO/data/datasets.py
HPO/data/repsol_dataset.py
HPO/data/supersets.py
HPO/data/teps_datasets.py
HPO/searchspaces/AttnNAS_config.py
HPO/searchspaces/DARTS_config.py
HPO/searchspaces/DARTS_cv_config.py
HPO/searchspaces/DARTS_new_config.py
HPO/searchspaces/DARTS_rerun_config.py
HPO/searchspaces/OOP_config.py
HPO/searchspaces/__init__.py
HPO/searchspaces/act_config.py
HPO/searchspaces/cell.py
HPO/searchspaces/cnn_config.py
HPO/searchspaces/graph_search_space.py
HPO/searchspaces/hierachical.py
HPO/searchspaces/mlp_config.py
HPO/searchspaces/nasbench301_configspace.py
HPO/searchspaces/nats_bench_config.py
HPO/searchspaces/resnet.py
HPO/searchspaces/spaces.py
HPO/searchspaces/utils.py
HPO/utils/ConfigStruct.py
HPO/utils/DARTS_utils.py
HPO/utils/FCN.py
HPO/utils/MultResAttn.py
HPO/utils/ResNet.py
HPO/utils/ResNet1d.py
HPO/utils/__init__.py
HPO/utils/augmentation.py
HPO/utils/autotrainer.py
HPO/utils/bayes.py
HPO/utils/benchmark_models.py
HPO/utils/critical-difference.py
HPO/utils/distilling.py
HPO/utils/ensemble.py
HPO/utils/files.py
HPO/utils/genotypes.py
HPO/utils/graph_ops.py
HPO/utils/graph_ops2d.py
HPO/utils/graph_ops3d.py
HPO/utils/graph_utils.py
HPO/utils/memory.py
HPO/utils/mlp.py
HPO/utils/model.py
HPO-0.4.dist-info/METADATA
HPO-0.4.dist-info/WHEEL
HPO-0.4.dist-info/top_level.txt
HPO-0.4.dist-info/RECORD
